mov_cli/__init__.py
mov_cli/cache.py
mov_cli/config.py
mov_cli/config.template.toml
mov_cli/download.py
mov_cli/errors.py
mov_cli/http_client.py
mov_cli/logger.py
mov_cli/plugins.py
mov_cli/scraper.py
mov_cli/cli/__init__.py
mov_cli/cli/__main__.py
mov_cli/cli/auto_select.py
mov_cli/cli/configuration.py
mov_cli/cli/episode.py
mov_cli/cli/main_loop.py
mov_cli/cli/play.py
mov_cli/cli/plugins.py
mov_cli/cli/random_tips.json
mov_cli/cli/scraper.py
mov_cli/cli/search.py
mov_cli/cli/ui.py
mov_cli/cli/watch_options.py
mov_cli/dev_cli/__init__.py
mov_cli/dev_cli/__main__.py
mov_cli/dev_cli/preview.py
mov_cli/iterfzf/LICENSE.txt
mov_cli/iterfzf/__init__.py
mov_cli/media/__init__.py
mov_cli/media/media.py
mov_cli/media/metadata.py
mov_cli/media/quality.py
mov_cli/players/__init__.py
mov_cli/players/custom_player.py
mov_cli/players/iina.py
mov_cli/players/mpv.py
mov_cli/players/player.py
mov_cli/players/syncplay.py
mov_cli/players/vlc.py
mov_cli/utils/__init__.py
mov_cli/utils/episode_selector.py
mov_cli/utils/ip.py
mov_cli/utils/paths.py
mov_cli/utils/platform.py
mov_cli/utils/slugify.py
mov_cli/utils/version.py
mov_cli/utils/scraper/__init__.py
mov_cli/utils/scraper/the_movie_db.py
mov_cli/utils/subtitles/__init__.py
mov_cli/utils/subtitles/iso_639.json
mov_cli/utils/subtitles/lang.py
mov_cli-4.4.19.dist-info/LICENSE
mov_cli-4.4.19.dist-info/METADATA
mov_cli-4.4.19.dist-info/WHEEL
mov_cli-4.4.19.dist-info/entry_points.txt
mov_cli-4.4.19.dist-info/top_level.txt
mov_cli-4.4.19.dist-info/RECORD
