Metadata-Version: 2.2
Name: mov-cli
Version: 4.4.19
Summary: Watch everything from your terminal.
Author-email: Pain <painedposeidon444@gmail.com>, Ananas <ananas@ananas.moe>, Goldy <goldy@devgoldy.xyz>
License: MIT License
Project-URL: GitHub, https://github.com/mov-cli/mov-cli
Project-URL: BugTracker, https://github.com/mov-cli/mov-cli/issues
Keywords: movie-cli,mov_cli
Classifier: Operating System :: Microsoft :: Windows :: Windows 11
Classifier: Operating System :: Microsoft :: Windows :: Windows 10
Classifier: Operating System :: POSIX :: Linux
Classifier: License :: OSI Approved :: MIT License
Classifier: Programming Language :: Python :: 3.8
Classifier: Programming Language :: Python :: 3.9
Classifier: Programming Language :: Python :: 3.10
Classifier: Programming Language :: Python :: 3.11
Classifier: Programming Language :: Python :: 3.12
Requires-Python: >=3.8
License-File: LICENSE
Requires-Dist: httpx
Requires-Dist: importlib-metadata; python_version < "3.8"
Requires-Dist: toml
Requires-Dist: devgoldyutils>=3.0.0
Requires-Dist: typer>=0.12.2
Requires-Dist: inquirer
Requires-Dist: beautifulsoup4
Requires-Dist: Unidecode
Requires-Dist: deprecation
Requires-Dist: packaging
Requires-Dist: thefuzz
Requires-Dist: python-decouple
Requires-Dist: mov-cli-test>=1.1.7
Provides-Extra: dev
Requires-Dist: ruff; extra == "dev"
Requires-Dist: build; extra == "dev"
Requires-Dist: devgoldyutils[pprint]>=2.5.7; extra == "dev"
Requires-Dist: Sphinx; extra == "dev"
Requires-Dist: sphinxext-opengraph; extra == "dev"
Requires-Dist: sphinx-inline-tabs; extra == "dev"
Requires-Dist: furo; extra == "dev"
Requires-Dist: myst-parser; extra == "dev"
Requires-Dist: sphinx-copybutton; extra == "dev"
